drf_nested_serializer/__init__.py
drf_nested_serializer/serializers.py
tests/__init__.py
tests/models.py
tests/serializers.py
tests/tests.py
tests/urls.py
tests/views.py
drf_nested_serializer-0.1.0.dist-info/LICENSE
drf_nested_serializer-0.1.0.dist-info/METADATA
drf_nested_serializer-0.1.0.dist-info/WHEEL
drf_nested_serializer-0.1.0.dist-info/top_level.txt
drf_nested_serializer-0.1.0.dist-info/RECORD
