Metadata-Version: 2.1
Name: drf-nested-serializer
Version: 0.1.0
Summary: nested serializer for django-rest-framework
Home-page: https://github.com/insung151/drf-nested-serializer
Author: Inseong Hwang
Author-email: insung151@naver.com
License: MIT
Keywords: drf restframework rest_framework django_rest_framework serializers def_nested_serializer
Platform: UNKNOWN
Classifier: Environment :: Web Environment
Classifier: Framework :: Django
Classifier: Intended Audience :: Developers
Classifier: Programming Language :: Python
Classifier: Topic :: Software Development
